[{"name": "尊享 坍雪寒裘捆绑包", "price": "481", "c5page": "https://www.c5game.com/dota/17918-S.html", "steamPage": "https://steamcommunity.com/market/listings/570}/Exalted Frost Avalanche Bundle", "hashName": "Exalted Frost Avalanche Bundle", "steamLeastSelling": "395.63"},{"name": "荒漠灼印", "price": "442.6", "c5page": "https://www.c5game.com/dota/797705432967938048-S.html", "steamPage": "https://steamcommunity.com/market/listings/570}/Desert Burn", "hashName": "Desert Burn", "steamLeastSelling": "468.77"},{"name": "2016年国际邀请赛亲笔签名：Amer 'Miracle-' Al-Barkawi", "price": "452.5", "c5page": "https://www.c5game.com/dota/16290494-S.html", "steamPage": "https://steamcommunity.com/market/listings/570}/International 2016 Autograph: Amer 'Miracle-' Al-Barkawi", "hashName": "International 2016 Autograph: Amer 'Miracle-' Al-Barkawi", "steamLeastSelling": "486.39"},{"name": "2017年国际邀请赛亲笔签名：Jesse 'JerAx' Vainikka", "price": "409.59", "c5page": "https://www.c5game.com/dota/553443643-S.html", "steamPage": "https://steamcommunity.com/market/listings/570}/International 2017 Autograph: Jesse 'JerAx' Vainikka", "hashName": "International 2017 Autograph: Jesse 'JerAx' Vainikka", "steamLeastSelling": "290.12"},{"name": "签名：'fy' Xu Linsen", "price": "414.99", "c5page": "https://www.c5game.com/dota/213929-S.html", "steamPage": "https://steamcommunity.com/market/listings/570}/Autograph: 'fy' Xu Linsen", "hashName": "Autograph: 'fy' Xu Linsen", "steamLeastSelling": "600"},{"name": "2015年国际邀请赛亲笔签名：Luo 'Ferrari_430' Feichi", "price": "482.5", "c5page": "https://www.c5game.com/dota/3516244-S.html", "steamPage": "https://steamcommunity.com/market/listings/570}/International 2015 Autograph: Luo 'Ferrari_430' Feichi", "hashName": "International 2015 Autograph: Luo 'Ferrari_430' Feichi", "steamLeastSelling": "291.90"},{"name": "血月烈印", "price": "420", "c5page": "https://www.c5game.com/dota/261950305-S.html", "steamPage": "https://steamcommunity.com/market/listings/570}/Mark of the Blood Moon", "hashName": "Mark of the Blood Moon", "steamLeastSelling": "672.01"},{"name": "纯正 签名：Luo 'Ferrari_430' Feichi", "price": "475.5", "c5page": "https://www.c5game.com/dota/32759-S.html", "steamPage": "https://steamcommunity.com/market/listings/570}/Genuine Autograph: Luo 'Ferrari_430' Feichi", "hashName": "Genuine Autograph: Luo 'Ferrari_430' Feichi", "steamLeastSelling": "995.99"},{"name": "独特 咬人箱罗克", "price": "427", "c5page": "https://www.c5game.com/dota/6403-S.html", "steamPage": "https://steamcommunity.com/market/listings/570}/Unusual Lockjaw the Boxhound", "hashName": "Unusual Lockjaw the Boxhound", "steamLeastSelling": "607.15"},{"name": "铭刻 魔族之颜", "price": "487.5", "c5page": "https://www.c5game.com/dota/18896-S.html", "steamPage": "https://steamcommunity.com/market/listings/570}/Inscribed Diabolic Aspect", "hashName": "Inscribed Diabolic Aspect", "steamLeastSelling": "888"},{"name": "高山行者的围巾", "price": "491.9", "c5page": "https://www.c5game.com/dota/8827-S.html", "steamPage": "https://steamcommunity.com/market/listings/570}/Alpine Stalker's Scarf", "hashName": "Alpine Stalker's Scarf", "steamLeastSelling": "778.98"},{"name": "纯正 纯金苍白之陵", "price": "429", "c5page": "https://www.c5game.com/dota/8459-S.html", "steamPage": "https://steamcommunity.com/market/listings/570}/Genuine Golden Pale Mausoleum", "hashName": "Genuine Golden Pale Mausoleum", "steamLeastSelling": "550"},{"name": "纯正 神秘 落难公主之服", "price": "489.5", "c5page": "https://www.c5game.com/dota/5968-S.html", "steamPage": "https://steamcommunity.com/market/listings/570}/Genuine Promo Vestments of the Fallen Princess", "hashName": "Genuine Promo Vestments of the Fallen Princess", "steamLeastSelling": "426.92"},{"name": "2015年珍宝之瓶-Mumu亲笔签名", "price": "413", "c5page": "https://www.c5game.com/dota/19988-S.html", "steamPage": "https://steamcommunity.com/market/listings/570}/Trove Carafe 2015 Autographed by Mumu", "hashName": "Trove Carafe 2015 Autographed by Mumu", "steamLeastSelling": "165.90"},{"name": "2019年国际邀请赛亲笔签名：David 'GoDz' Parker", "price": "435.34", "c5page": "https://www.c5game.com/dota/553490617-S.html", "steamPage": "https://steamcommunity.com/market/listings/570}/International 2019 Autograph: David 'GoDz' Parker", "hashName": "International 2019 Autograph: David 'GoDz' Parker", "steamLeastSelling": "9.25"},{"name": "亲笔签名 白虎", "price": "418", "c5page": "https://www.c5game.com/dota/11056-S.html", "steamPage": "https://steamcommunity.com/market/listings/570}/Autographed Baekho", "hashName": "Autographed Baekho", "steamLeastSelling": "19"},{"name": "2017年国际邀请赛亲笔签名：Anathan 'ana' Pham", "price": "496.5", "c5page": "https://www.c5game.com/dota/553443645-S.html", "steamPage": "https://steamcommunity.com/market/listings/570}/International 2017 Autograph: Anathan 'ana' Pham", "hashName": "International 2017 Autograph: Anathan 'ana' Pham", "steamLeastSelling": "298.31"},{"name": "棱彩：灰烬之焰", "price": "468.8", "c5page": "https://www.c5game.com/dota/957106-S.html", "steamPage": "https://steamcommunity.com/market/listings/570}/Prismatic: Ember Flame", "hashName": "Prismatic: Ember Flame", "steamLeastSelling": "517.57"},{"name": "纯正 箭雨之弓", "price": "429", "c5page": "https://www.c5game.com/dota/6507-S.html", "steamPage": "https://steamcommunity.com/market/listings/570}/Genuine Rainmaker", "hashName": "Genuine Rainmaker", "steamLeastSelling": "489.99"},{"name": "冥灵 胡小桃", "price": "400", "c5page": "https://www.c5game.com/dota/10293-S.html", "steamPage": "https://steamcommunity.com/market/listings/570}/Corrupted Shagbark", "hashName": "Corrupted Shagbark", "steamLeastSelling": "29.82"},{"name": "亲笔签名 纯金岩晶碎屑", "price": "400", "c5page": "https://www.c5game.com/dota/13814039-S.html", "steamPage": "https://steamcommunity.com/market/listings/570}/Autographed Golden Latticean Shards", "hashName": "Autographed Golden Latticean Shards", "steamLeastSelling": "405.77"},{"name": "猩红顿悟翔翼", "price": "441.5", "c5page": "https://www.c5game.com/dota/553484145-S.html", "steamPage": "https://steamcommunity.com/market/listings/570}/Crimson Flight of Epiphany", "hashName": "Crimson Flight of Epiphany", "steamLeastSelling": "596"},{"name": "独特 巨鸟多多", "price": "434.5", "c5page": "https://www.c5game.com/dota/7899-S.html", "steamPage": "https://steamcommunity.com/market/listings/570}/Unusual Drodo the Druffin", "hashName": "Unusual Drodo the Druffin", "steamLeastSelling": "618.24"},{"name": "独特 机械咬人箱", "price": "423.5", "c5page": "https://www.c5game.com/dota/8778-S.html", "steamPage": "https://steamcommunity.com/market/listings/570}/Unusual Mechjaw the Boxhound", "hashName": "Unusual Mechjaw the Boxhound", "steamLeastSelling": "570"},{"name": "纯正 纯金待宰羔羊神杖", "price": "401.85", "c5page": "https://www.c5game.com/dota/7502-S.html", "steamPage": "https://steamcommunity.com/market/listings/570}/Genuine Golden Lamb to the Slaughter", "hashName": "Genuine Golden Lamb to the Slaughter", "steamLeastSelling": "609.47"},{"name": "独特 恶魔铁匠", "price": "470", "c5page": "https://www.c5game.com/dota/7898-S.html", "steamPage": "https://steamcommunity.com/market/listings/570}/Unusual Murrissey the Smeevil", "hashName": "Unusual Murrissey the Smeevil", "steamLeastSelling": "596.44"},{"name": "纯正 高阶逐巫武士", "price": "500", "c5page": "https://www.c5game.com/dota/62244396-S.html", "steamPage": "https://steamcommunity.com/market/listings/570}/Genuine Grand Witch Hunter Templar", "hashName": "Genuine Grand Witch Hunter Templar", "steamLeastSelling": "723.70"},{"name": "铭刻 猩红顿悟翔翼", "price": "485", "c5page": "https://www.c5game.com/dota/553484162-S.html", "steamPage": "https://steamcommunity.com/market/listings/570}/Inscribed Crimson Flight of Epiphany", "hashName": "Inscribed Crimson Flight of Epiphany", "steamLeastSelling": "780"},{"name": "棱彩：夏日温情", "price": "424", "c5page": "https://www.c5game.com/dota/443093-S.html", "steamPage": "https://steamcommunity.com/market/listings/570}/Prismatic: Summer Warmth", "hashName": "Prismatic: Summer Warmth", "steamLeastSelling": "2,251.59"},{"name": "龙焰信徒", "price": "454.65", "c5page": "https://www.c5game.com/dota/7455804-S.html", "steamPage": "https://steamcommunity.com/market/listings/570}/Disciple of the Wyrmwrought Flame", "hashName": "Disciple of the Wyrmwrought Flame", "steamLeastSelling": "600"},{"name": "渊海绝影护甲", "price": "479.5", "c5page": "https://www.c5game.com/dota/796570780744548353-S.html", "steamPage": "https://steamcommunity.com/market/listings/570}/Shadow in the Deep Armor", "hashName": "Shadow in the Deep Armor", "steamLeastSelling": "615.83"},{"name": "暗黑奇艺披风", "price": "499.5", "c5page": "https://www.c5game.com/dota/385276-S.html", "steamPage": "https://steamcommunity.com/market/listings/570}/Dark Artistry Cape", "hashName": "Dark Artistry Cape", "steamLeastSelling": "690"},{"name": "亲笔签名 木偶困境之炬", "price": "400", "c5page": "https://www.c5game.com/dota/27831-S.html", "steamPage": "https://steamcommunity.com/market/listings/570}/Autographed Torch of Fantoccini's Dilemma", "hashName": "Autographed Torch of Fantoccini's Dilemma", "steamLeastSelling": "706.18"},{"name": "纯正 毛绒胡小桃", "price": "450", "c5page": "https://www.c5game.com/dota/5067-S.html", "steamPage": "https://steamcommunity.com/market/listings/570}/Genuine Shagbark the Plush", "hashName": "Genuine Shagbark the Plush", "steamLeastSelling": "575"},{"name": "棱彩：绒毛胡桃", "price": "445.7", "c5page": "https://www.c5game.com/dota/229239-S.html", "steamPage": "https://steamcommunity.com/market/listings/570}/Prismatic: Plushy Shag", "hashName": "Prismatic: Plushy Shag", "steamLeastSelling": "650.68"},{"name": "纯正 签名：Xu 'BurNIng' Zhilei", "price": "498.5", "c5page": "https://www.c5game.com/dota/842650-S.html", "steamPage": "https://steamcommunity.com/market/listings/570}/Genuine Autograph: Xu 'BurNIng' Zhilei", "hashName": "Genuine Autograph: Xu 'BurNIng' Zhilei", "steamLeastSelling": "345"},{"name": "尊享 擎天大圣捆绑包", "price": "424.21", "c5page": "https://www.c5game.com/dota/320787117-S.html", "steamPage": "https://steamcommunity.com/market/listings/570}/Exalted Great Sage's Reckoning Bundle", "hashName": "Exalted Great Sage's Reckoning Bundle", "steamLeastSelling": "472.55"},{"name": "纯正 永恒思维意识", "price": "486.48", "c5page": "https://www.c5game.com/dota/6796-S.html", "steamPage": "https://steamcommunity.com/market/listings/570}/Genuine Perceptions of the Eternal Mind", "hashName": "Genuine Perceptions of the Eternal Mind", "steamLeastSelling": "729.44"},{"name": "猩红岩晶云阶", "price": "407", "c5page": "https://www.c5game.com/dota/553484143-S.html", "steamPage": "https://steamcommunity.com/market/listings/570}/Crimson Latticean Hierarchy", "hashName": "Crimson Latticean Hierarchy", "steamLeastSelling": "575"},{"name": "2016年国际邀请赛亲笔签名：Chu 'Shadow' Zeyu", "price": "499", "c5page": "https://www.c5game.com/dota/16655170-S.html", "steamPage": "https://steamcommunity.com/market/listings/570}/International 2016 Autograph: Chu 'Shadow' Zeyu", "hashName": "International 2016 Autograph: Chu 'Shadow' Zeyu", "steamLeastSelling": "390.59"},{"name": "铭刻 龙焰信徒", "price": "497.2", "c5page": "https://www.c5game.com/dota/12292095-S.html", "steamPage": "https://steamcommunity.com/market/listings/570}/Inscribed Disciple of the Wyrmwrought Flame", "hashName": "Inscribed Disciple of the Wyrmwrought Flame", "steamLeastSelling": "712.89"}]